<annotation>
	<folder>JPEGImages</folder>
	<filename>97.jpg</filename>
	<path>D:\deeplearning_github\insects_detection\VOCdevkit\VOC2007\JPEGImages\97.jpg</path>
	<source>
		<database>Unknown</database>
	</source>
	<size>
		<width>2572</width>
		<height>1819</height>
		<depth>3</depth>
	</size>
	<segmented>0</segmented>
	<object>
		<name>huangchong</name>
		<pose>Unspecified</pose>
		<truncated>0</truncated>
		<difficult>0</difficult>
		<bndbox>
			<xmin>300</xmin>
			<ymin>566</ymin>
			<xmax>2267</xmax>
			<ymax>1462</ymax>
		</bndbox>
	</object>
</annotation>
